instaui_arco/__init__.py
instaui_arco/_settings.py
instaui_arco/_use_tools/locale.py
instaui_arco/component_types.py
instaui_arco/components/_utils.py
instaui_arco/components/affix.py
instaui_arco/components/alert.py
instaui_arco/components/anchor.py
instaui_arco/components/auto_complete.py
instaui_arco/components/avatar.py
instaui_arco/components/back_top.py
instaui_arco/components/badge.py
instaui_arco/components/breadcrumb.py
instaui_arco/components/button.py
instaui_arco/components/calendar.py
instaui_arco/components/card.py
instaui_arco/components/carousel.py
instaui_arco/components/cascader.py
instaui_arco/components/checkbox.py
instaui_arco/components/collapse.py
instaui_arco/components/color_picker.py
instaui_arco/components/comment.py
instaui_arco/components/config_provider.py
instaui_arco/components/date_picker.py
instaui_arco/components/descriptions.py
instaui_arco/components/divider.py
instaui_arco/components/drawer.py
instaui_arco/components/dropdown.py
instaui_arco/components/empty.py
instaui_arco/components/form.py
instaui_arco/components/icon.py
instaui_arco/components/image.py
instaui_arco/components/input.py
instaui_arco/components/input_number.py
instaui_arco/components/input_password.py
instaui_arco/components/input_search.py
instaui_arco/components/input_tag.py
instaui_arco/components/layout.py
instaui_arco/components/layout_content.py
instaui_arco/components/layout_footer.py
instaui_arco/components/layout_header.py
instaui_arco/components/layout_sider.py
instaui_arco/components/link.py
instaui_arco/components/list.py
instaui_arco/components/mention.py
instaui_arco/components/menu.py
instaui_arco/components/modal.py
instaui_arco/components/overflow_list.py
instaui_arco/components/page_header.py
instaui_arco/components/pagination.py
instaui_arco/components/pop_confirm.py
instaui_arco/components/popover.py
instaui_arco/components/progress.py
instaui_arco/components/radio.py
instaui_arco/components/radio_group.py
instaui_arco/components/rate.py
instaui_arco-0.1.4.dist-info/LICENSE
instaui_arco-0.1.4.dist-info/METADATA
instaui_arco-0.1.4.dist-info/WHEEL
instaui_arco-0.1.4.dist-info/RECORD
