Metadata-Version: 2.3
Name: instaui-arco
Version: 0.1.4
Summary: 
Author: CrystalWindSnake
Author-email: 568166495@qq.com
Requires-Python: >=3.8,<3.13
Classifier: Programming Language :: Python :: 3
Classifier: Programming Language :: Python :: 3.8
Classifier: Programming Language :: Python :: 3.9
Classifier: Programming Language :: Python :: 3.10
Classifier: Programming Language :: Python :: 3.11
Classifier: Programming Language :: Python :: 3.12
Requires-Dist: instaui (>=0.1.0,<0.2.0)
